solyanka/__init__.py
solyanka/pattern_preview.py
solyanka/transaction_patterns/__init__.py
solyanka/transaction_patterns/service.py
solyanka/transaction_patterns/data/brazil.yml
solyanka/transaction_patterns/data/colombia.yml
solyanka/transaction_patterns/data/eea.yml
solyanka/transaction_patterns/data/france.yml
solyanka/transaction_patterns/data/general.yml
solyanka/transaction_patterns/data/georgia.yml
solyanka/transaction_patterns/data/germany.yml
solyanka/transaction_patterns/data/hungary.yml
solyanka/transaction_patterns/data/indonesia.yml
solyanka/transaction_patterns/data/japan.yml
solyanka/transaction_patterns/data/laos.yml
solyanka/transaction_patterns/data/latvia.yml
solyanka/transaction_patterns/data/malaysia.yml
solyanka/transaction_patterns/data/oae.yml
solyanka/transaction_patterns/data/oman.yml
solyanka/transaction_patterns/data/portugal.yml
solyanka/transaction_patterns/data/schema.json
solyanka/transaction_patterns/data/spain.yml
solyanka/transaction_patterns/data/thailand.yml
solyanka/transaction_patterns/data/turkey.yml
solyanka/transaction_patterns/data/uae.yml
solyanka/transaction_patterns/data/uk.yml
solyanka/transaction_patterns/data/ukraine.yml
solyanka/transaction_patterns/data/usa.yml
solyanka/transaction_patterns/data/vietnam.yml
solyanka-0.3.3.1.dist-info/METADATA
solyanka-0.3.3.1.dist-info/WHEEL
solyanka-0.3.3.1.dist-info/licenses/LICENSE
solyanka-0.3.3.1.dist-info/RECORD
