Metadata-Version: 2.4
Name: solyanka
Version: 0.3.3.1
Summary: Transaction pattern utilities and dataset for statement generators
Author-email: Development Team <dev@company.com>
License:     MIT License
License-File: LICENSE
Requires-Python: >=3.11
Requires-Dist: pyyaml>=6.0
Provides-Extra: dev
Requires-Dist: jsonschema>=4.23; extra == 'dev'
Requires-Dist: pytest>=8.2; extra == 'dev'
